asteg/__init__.py
asteg/asteg_cli.py
asteg-0.1.5.dist-info/LICENSE
asteg-0.1.5.dist-info/METADATA
asteg-0.1.5.dist-info/WHEEL
asteg-0.1.5.dist-info/entry_points.txt
asteg-0.1.5.dist-info/top_level.txt
asteg-0.1.5.dist-info/RECORD
