Metadata-Version: 2.1
Name: asteg
Version: 0.1.5
Summary: Steganography : Hiding text or file inside an audio
Home-page: https://github.com/rafiibrahim8/asteg
Author: Ibrahim Rafi
Author-email: me@ibrahimrafi.me
License: MIT
Download-URL: https://github.com/rafiibrahim8/asteg/archive/v0.1.5.tar.gz
Keywords: asteg,steganography,audio
Platform: any
Classifier: Development Status :: 3 - Alpha
Classifier: Intended Audience :: Science/Research
Classifier: Topic :: Security :: Cryptography
Classifier: License :: OSI Approved :: MIT License
Classifier: Programming Language :: Python :: 3
Classifier: Programming Language :: Python :: 3.4
Classifier: Programming Language :: Python :: 3.5
Classifier: Programming Language :: Python :: 3.6
Classifier: Programming Language :: Python :: 3.7
Classifier: Programming Language :: Python :: 3.8
Classifier: Programming Language :: Python :: 3.9
Requires-Dist: pydub
Requires-Dist: numpy
Requires-Dist: scipy
